<?xml version="1.0" encoding="UTF-8" standalone="yes"?>
<F_entailment_graph nodeNum="2">
    <node id="317673.txt_1_0" modality="FALSE" explicit_context="317673.txt" implicit_context="" focus="Seating" implicit_focus="">
        <original_text>Seating is very cramped</original_text>
        <correct_text></correct_text>
    </node>
    <node id="317673.txt_1_1" modality="FALSE" explicit_context="317673.txt" implicit_context="" focus="Seating" implicit_focus="">
        <original_text>Seating is cramped</original_text>
        <correct_text></correct_text>
    </node>
    <edge id="317673.txt_1_0-317673.txt_1_1" source="317673.txt_1_0" target="317673.txt_1_1"/>
</F_entailment_graph>
